{
  "generator_version":"UAV2_gen12",
  "name":"design_7103_6fa58a72407c4495b27f771ad25849c7_dw",
  "hub":{
    "node_type":"ConnectedHub4_Sym_Aligned",
    "mainSegment":{
      "node_type":"CrossSegment",
      "armLength":293.5481409094857,
      "sideSegment":{
        "node_type":"PropArm",
        "armLength":354.35001421627567,
        "motor":{
          "motorType":"t_motor_MN4012KV400"
        },
        "prop":{
          "propType":"apc_propellers_15x10E"
        },
        "flange":{
          "offset":-31.778488610173973,
          "angle":270.0
        }
      },
      "centerSegment":{
        "node_type":"AngledPropArm",
        "armLength":208.92196244910588,
        "motor":{
          "motorType":"t_motor_MN5212KV340"
        },
        "prop":{
          "propType":"apc_propellers_15x10"
        }
      }
    }
  },
  "fuselageWithComponents":{
    "node_type":"DualBatteryFuselageWithComponents",
    "battery":{
      "batteryType":"TattuPlus15C16000mAh12S1Pcompact"
    },
    "fuselage":{
      "length":217.5,
      "vertDiameter":225.0,
      "horzDiameter":528.9,
      "floorHeight":37.5,
      "battery1X":0.0,
      "battery1Y":-34.5,
      "battery2X":0.0,
      "battery2Y":47.5,
      "rpmX":0.0,
      "rpmY":-166.3,
      "autoPilotX":0.0,
      "autoPilotY":110.0,
      "currentX":0.0,
      "currentY":-146.15,
      "voltageX":0.0,
      "voltageY":163.8,
      "gpsX":0.0,
      "gpsY":-106.0,
      "varioX":0.0,
      "varioY":142.15
    }
  }
}