{
  "generator_version":"UAV2_gen12",
  "name":"design_26893_83c95594000945e29819a6a5ed018b3d_s",
  "hub":{
    "node_type":"ConnectedHub4_Sym",
    "mainSegment":{
      "node_type":"BranchSegment_Sym",
      "armLength":175.1047462667339,
      "angle":180.0,
      "mainSegment":{
        "node_type":"PropArm",
        "armLength":275.6777895733202,
        "motor":{
          "motorType":"kde_direct_KDE600XF_530_G3"
        },
        "prop":{
          "propType":"apc_propellers_18x8E"
        },
        "flange":{
          "offset":-20.05340229417113,
          "angle":0.0
        }
      }
    }
  },
  "fuselageWithComponents":{
    "node_type":"SingleBatteryFuselageWithComponents",
    "battery":{
      "batteryType":"Tattu25C9000mAh6S1P"
    },
    "fuselage":{
      "length":208.0,
      "vertDiameter":109.5,
      "horzDiameter":341.4,
      "floorHeight":18.25,
      "batteryX":0.0,
      "batteryY":6.0,
      "rpmX":0.0,
      "rpmY":-103.8,
      "autoPilotX":0.0,
      "autoPilotY":47.5,
      "currentX":0.0,
      "currentY":-83.65,
      "voltageX":0.0,
      "voltageY":101.3,
      "gpsX":0.0,
      "gpsY":-43.5,
      "varioX":0.0,
      "varioY":79.65
    }
  }
}