{
  "generator_version":"UAV2_gen12",
  "name":"design_286_6a5a0243fb0c4cc995a2ef98775ea0b5_dw_dl",
  "hub":{
    "node_type":"ConnectedHub6_1_2_2_1",
    "frontCenterSegment":{
      "node_type":"BendSegment",
      "angle":-90.0,
      "armLength":124.58353700278289,
      "mainSegment":{
        "node_type":"PropArm",
        "armLength":182.79283944274997,
        "motor":{
          "motorType":"t_motor_MN3520KV400"
        },
        "prop":{
          "propType":"apc_propellers_15x8"
        },
        "flange":{
          "offset":-42.40303016080155,
          "angle":0.0
        }
      }
    },
    "frontSegment":{
      "node_type":"PropArm",
      "armLength":330.3105875971183,
      "motor":{
        "motorType":"kde_direct_KDE600XF_530_G3"
      },
      "prop":{
        "propType":"apc_propellers_16x8"
      },
      "flange":{
        "offset":26.130460426047037,
        "angle":173.72894952167917
      }
    },
    "rearSegment":{
      "node_type":"PropArm",
      "armLength":431.4058512208481,
      "motor":{
        "motorType":"t_motor_MN3520KV400"
      },
      "prop":{
        "propType":"apc_propellers_17x4W"
      },
      "flange":{
        "offset":-19.083944853410873,
        "angle":270.0
      }
    },
    "rearCenterSegment":{
      "node_type":"PropArm",
      "armLength":455.52936763956916,
      "motor":{
        "motorType":"t_motor_AT4120KV500"
      },
      "prop":{
        "propType":"apc_propellers_18x8E"
      },
      "flange":{
        "offset":-41.16100411874065,
        "angle":174.32605200027112
      }
    }
  },
  "fuselageWithComponents":{
    "node_type":"DualBatteryFuselageWithComponents",
    "battery":{
      "batteryType":"TattuPlus25C22000mAh12S1PAGRI"
    },
    "fuselage":{
      "length":471.0,
      "vertDiameter":258.0,
      "horzDiameter":459.9,
      "floorHeight":43.0,
      "battery1X":-117.75,
      "battery1Y":6.0,
      "battery2X":118.75,
      "battery2Y":6.0,
      "rpmX":0.0,
      "rpmY":-143.3,
      "autoPilotX":0.0,
      "autoPilotY":87.0,
      "currentX":0.0,
      "currentY":-123.15,
      "voltageX":0.0,
      "voltageY":140.8,
      "gpsX":0.0,
      "gpsY":-83.0,
      "varioX":0.0,
      "varioY":119.15
    }
  }
}