{
  "generator_version":"UAV2_gen12",
  "name":"design_32878_bbc237ec2870456fa469ee7eb17fe97f_s",
  "hub":{
    "node_type":"ConnectedHub6_1_2_2_1",
    "frontCenterSegment":{
      "node_type":"PropArm",
      "armLength":357.3154376827258,
      "motor":{
        "motorType":"t_motor_MN3515KV400"
      },
      "prop":{
        "propType":"apc_propellers_17x8E"
      },
      "flange":{
        "offset":26.211862148098845,
        "angle":90.0
      }
    },
    "frontSegment":{
      "node_type":"PropArm",
      "armLength":78.96915315922243,
      "motor":{
        "motorType":"t_motor_MN4012KV400"
      },
      "prop":{
        "propType":"apc_propellers_16x4E"
      },
      "flange":{
        "offset":33.659705668189574,
        "angle":0.0
      }
    },
    "rearSegment":{
      "node_type":"PropArm",
      "armLength":360.141845468587,
      "motor":{
        "motorType":"t_motor_AT4125KV540"
      },
      "prop":{
        "propType":"apc_propellers_17x8E"
      },
      "flange":{
        "offset":-47.93673469658041,
        "angle":0.0
      }
    },
    "rearCenterSegment":{
      "node_type":"AngledPropArm",
      "armLength":108.1067313065852,
      "motor":{
        "motorType":"kde_direct_KDE700XF_535_G3"
      },
      "prop":{
        "propType":"apc_propellers_18x8"
      }
    }
  },
  "fuselageWithComponents":{
    "node_type":"SingleBatteryFuselageWithComponents",
    "battery":{
      "batteryType":"TurnigyGraphene1500mAh3S75C"
    },
    "fuselage":{
      "length":90.0,
      "vertDiameter":52.5,
      "horzDiameter":323.4,
      "floorHeight":8.75,
      "batteryX":0.0,
      "batteryY":6.0,
      "rpmX":0.0,
      "rpmY":-97.8,
      "autoPilotX":0.0,
      "autoPilotY":41.5,
      "currentX":0.0,
      "currentY":-77.65,
      "voltageX":0.0,
      "voltageY":95.3,
      "gpsX":0.0,
      "gpsY":-37.5,
      "varioX":0.0,
      "varioY":73.65
    }
  }
}