{
  "generator_version":"UAV2_gen12",
  "name":"design_612_9a5f8226f995460183f9becb0121fd49_s",
  "hub":{
    "node_type":"ConnectedHub6_2_2_2",
    "frontSegment":{
      "node_type":"AngledPropArm",
      "armLength":446.3660480712966,
      "motor":{
        "motorType":"t_motor_U7_V2.0KV490"
      },
      "prop":{
        "propType":"apc_propellers_17x8E"
      }
    },
    "middleSegment":{
      "node_type":"BranchWithTopSegment_Asym",
      "armLength":303.40872361329014,
      "angle":180.0,
      "leftSegment":{
        "node_type":"BranchSegment_Sym",
        "armLength":102.40520223014991,
        "angle":120.0,
        "mainSegment":{
          "node_type":"BranchSegment_Sym",
          "armLength":292.1236554455147,
          "angle":180.0,
          "mainSegment":{
            "node_type":"PropArm",
            "armLength":407.797848442055,
            "motor":{
              "motorType":"t_motor_AT4120KV500"
            },
            "prop":{
              "propType":"apc_propellers_16x7"
            },
            "flange":{
              "offset":-12.236192668194555,
              "angle":0.0
            }
          }
        }
      },
      "rightSegment":{
        "node_type":"AngledPropArm",
        "armLength":101.73467575439528,
        "motor":{
          "motorType":"kde_direct_KDE5215XF_435"
        },
        "prop":{
          "propType":"apc_propellers_17x10N"
        }
      },
      "topSegment":{
        "node_type":"SidewaysBendSegment",
        "angle":-68.8478374084816,
        "armLength":231.04150148550062,
        "mainSegment":{
          "node_type":"PropArm",
          "armLength":450.0032727289266,
          "motor":{
            "motorType":"kde_direct_KDE3520XF_400"
          },
          "prop":{
            "propType":"apc_propellers_16x10E"
          },
          "flange":{
            "offset":2.0067012489466762,
            "angle":0.0
          }
        }
      }
    },
    "rearSegment":{
      "node_type":"PropArm",
      "armLength":204.40700150875,
      "motor":{
        "motorType":"t_motor_MN4012KV340"
      },
      "prop":{
        "propType":"apc_propellers_16x12E"
      },
      "flange":{
        "offset":27.917770225048926,
        "angle":0.0
      }
    }
  },
  "fuselageWithComponents":{
    "node_type":"SingleBatteryFuselageWithComponents",
    "battery":{
      "batteryType":"TattuPlus15C16000mAh12S1P"
    },
    "fuselage":{
      "length":224.0,
      "vertDiameter":244.5,
      "horzDiameter":420.9,
      "floorHeight":40.75,
      "batteryX":0.0,
      "batteryY":6.0,
      "rpmX":0.0,
      "rpmY":-130.3,
      "autoPilotX":0.0,
      "autoPilotY":74.0,
      "currentX":0.0,
      "currentY":-110.15,
      "voltageX":0.0,
      "voltageY":127.8,
      "gpsX":0.0,
      "gpsY":-70.0,
      "varioX":0.0,
      "varioY":106.15
    }
  }
}