{
  "generator_version":"UAV2_gen12",
  "name":"design_1328_7556af3b18aa4d62904fccdc64a85027_s",
  "hub":{
    "node_type":"ConnectedHub6_2_2_2",
    "frontSegment":{
      "node_type":"DoubleBendSegment",
      "angle":-90.0,
      "arm1Length":302.2443362058316,
      "arm2Length":309.6828004831616,
      "mainSegment":{
        "node_type":"PropArm",
        "armLength":483.43152804382794,
        "motor":{
          "motorType":"kde_direct_KDE700XF_535_G3"
        },
        "prop":{
          "propType":"apc_propellers_18x12E"
        },
        "flange":{
          "offset":29.111055300513527,
          "angle":0.0
        }
      }
    },
    "middleSegment":{
      "node_type":"BendSegment",
      "angle":-90.0,
      "armLength":375.39580506663,
      "mainSegment":{
        "node_type":"AngledWingArm",
        "arm1Length":68.67605587105294,
        "arm2Length":125.73584252657088,
        "wing":{
          "wingType":"Wing_horiz_hole",
          "nacaProfile":"2409",
          "span":606.6617043006977,
          "chordInner":411.38096096053147,
          "chordOuter":61.606245725856624,
          "taperOffset":false,
          "aileronBias":0.18380162388967097,
          "flapBias":0.4618117875273299,
          "load":462.67325985275596,
          "tubeOffset":51.489621171901575,
          "tubeRot":270.0
        },
        "servo":{
          "servoType":"Hitec_HS_225BB"
        }
      }
    },
    "rearSegment":{
      "node_type":"PropArm",
      "armLength":121.0712149208346,
      "motor":{
        "motorType":"kde_direct_KDE4213XF_360"
      },
      "prop":{
        "propType":"apc_propellers_15x10E"
      },
      "flange":{
        "offset":2.019100780574149,
        "angle":270.0
      }
    }
  },
  "fuselageWithComponents":{
    "node_type":"SingleBatteryFuselageWithComponents",
    "battery":{
      "batteryType":"TattuPlus15C16000mAh12S1Pcompact"
    },
    "fuselage":{
      "length":217.5,
      "vertDiameter":225.0,
      "horzDiameter":405.9,
      "floorHeight":37.5,
      "batteryX":0.0,
      "batteryY":6.0,
      "rpmX":0.0,
      "rpmY":-125.3,
      "autoPilotX":0.0,
      "autoPilotY":69.0,
      "currentX":0.0,
      "currentY":-105.15,
      "voltageX":0.0,
      "voltageY":122.8,
      "gpsX":0.0,
      "gpsY":-65.0,
      "varioX":0.0,
      "varioY":101.15
    }
  }
}