{
  "generator_version":"UAV2_gen12",
  "name":"design_7366_f0d89d545f7647b395e24fafad18e5a3_dw",
  "hub":{
    "node_type":"ConnectedHub6_2_2_2",
    "frontSegment":{
      "node_type":"AngledPropArm",
      "armLength":168.2151913845695,
      "motor":{
        "motorType":"t_motor_AT4130KV450"
      },
      "prop":{
        "propType":"apc_propellers_15x6"
      }
    },
    "middleSegment":{
      "node_type":"WingArm",
      "armLength":96.05353515455766,
      "wing":{
        "wingType":"Wing_vert_hole",
        "nacaProfile":"4506",
        "span":1133.5977683077558,
        "chordInner":194.8243099139487,
        "chordOuter":171.13513636090337,
        "taperOffset":false,
        "aileronBias":0.16373620274765455,
        "flapBias":0.6205284422103537,
        "load":361.0223813188434,
        "tubeOffset":27.21287884542143,
        "tubeRot":291.72294861827686
      },
      "servo":{
        "servoType":"Hitec_HS_45HB"
      }
    },
    "rearSegment":{
      "node_type":"PropArm",
      "armLength":327.8396221093122,
      "motor":{
        "motorType":"t_motor_MN3520KV400"
      },
      "prop":{
        "propType":"apc_propellers_17x6"
      },
      "flange":{
        "offset":-18.623194635872544,
        "angle":0.0
      }
    }
  },
  "fuselageWithComponents":{
    "node_type":"DualBatteryFuselageWithComponents",
    "battery":{
      "batteryType":"Tattu25C10000mAh4S1P"
    },
    "fuselage":{
      "length":169.0,
      "vertDiameter":97.5,
      "horzDiameter":405.9,
      "floorHeight":16.25,
      "battery1X":0.0,
      "battery1Y":-14.0,
      "battery2X":0.0,
      "battery2Y":27.0,
      "rpmX":0.0,
      "rpmY":-125.3,
      "autoPilotX":0.0,
      "autoPilotY":69.0,
      "currentX":0.0,
      "currentY":-105.15,
      "voltageX":0.0,
      "voltageY":122.8,
      "gpsX":0.0,
      "gpsY":-65.0,
      "varioX":0.0,
      "varioY":101.15
    }
  }
}