{
  "generator_version":"UAV2_gen12",
  "name":"design_40888_d95093c3068545aa828e6a6b6aa667fa_dw_dl",
  "hub":{
    "node_type":"ConnectedHub4_2_2",
    "frontSegment":{
      "node_type":"PropArm",
      "armLength":135.00179610911437,
      "motor":{
        "motorType":"t_motor_AT4120KV500"
      },
      "prop":{
        "propType":"apc_propellers_20x10W"
      },
      "flange":{
        "offset":31.362992053932913,
        "angle":0.0
      }
    },
    "rearSegment":{
      "node_type":"CrossSegment",
      "armLength":354.86283982257635,
      "sideSegment":{
        "node_type":"DoubleBendSegment",
        "angle":-90.0,
        "arm1Length":437.27173735037917,
        "arm2Length":257.1777215650997,
        "mainSegment":{
          "node_type":"AngledPropArm",
          "armLength":290.856424203222,
          "motor":{
            "motorType":"t_motor_U7_V2.0KV490"
          },
          "prop":{
            "propType":"apc_propellers_16x8"
          }
        }
      },
      "centerSegment":{
        "node_type":"AngledPropArm",
        "armLength":57.53542391997568,
        "motor":{
          "motorType":"kde_direct_KDE600XF_530_G3"
        },
        "prop":{
          "propType":"apc_propellers_16x5_5MR"
        }
      }
    }
  },
  "fuselageWithComponents":{
    "node_type":"DualBatteryFuselageWithComponents",
    "battery":{
      "batteryType":"Tattu25C9000mAh6S1P"
    },
    "fuselage":{
      "length":417.0,
      "vertDiameter":109.5,
      "horzDiameter":341.4,
      "floorHeight":18.25,
      "battery1X":-104.25,
      "battery1Y":6.0,
      "battery2X":105.25,
      "battery2Y":6.0,
      "rpmX":0.0,
      "rpmY":-103.8,
      "autoPilotX":0.0,
      "autoPilotY":47.5,
      "currentX":0.0,
      "currentY":-83.65,
      "voltageX":0.0,
      "voltageY":101.3,
      "gpsX":0.0,
      "gpsY":-43.5,
      "varioX":0.0,
      "varioY":79.65
    }
  }
}