{
  "generator_version":"UAV2_gen12",
  "name":"design_3378_a49e5071fc244fbda71efcd89387f905_s",
  "hub":{
    "node_type":"ConnectedHub6_Sym",
    "mainSegment":{
      "node_type":"PropArm",
      "armLength":302.0188357199056,
      "motor":{
        "motorType":"t_motor_AntigravityMN6007IIKV320"
      },
      "prop":{
        "propType":"apc_propellers_14x14N"
      },
      "flange":{
        "offset":23.456441768003202,
        "angle":209.42830523726434
      }
    }
  },
  "fuselageWithComponents":{
    "node_type":"SingleBatteryFuselageWithComponents",
    "battery":{
      "batteryType":"TurnigyGraphene1000mAh2S75C"
    },
    "fuselage":{
      "length":84.0,
      "vertDiameter":52.5,
      "horzDiameter":311.4,
      "floorHeight":8.75,
      "batteryX":-5.0,
      "batteryY":6.0,
      "rpmX":-5.0,
      "rpmY":-93.8,
      "autoPilotX":-5.0,
      "autoPilotY":37.5,
      "currentX":-5.0,
      "currentY":-73.65,
      "voltageX":-5.0,
      "voltageY":91.3,
      "gpsX":-5.0,
      "gpsY":-33.5,
      "varioX":-5.0,
      "varioY":69.65
    }
  }
}