{
  "generator_version":"UAV2_gen12",
  "name":"design_29800_ea919944ff6043238b0d61b75d42b16d_s",
  "hub":{
    "node_type":"ConnectedHub6_1_2_2_1",
    "frontCenterSegment":{
      "node_type":"BendSegment",
      "angle":-90.0,
      "armLength":116.96644472753216,
      "mainSegment":{
        "node_type":"AngledPropArm",
        "armLength":349.90212011222235,
        "motor":{
          "motorType":"kde_direct_KDE3520XF_400"
        },
        "prop":{
          "propType":"apc_propellers_15x5_5MR"
        }
      }
    },
    "frontSegment":{
      "node_type":"PropArm",
      "armLength":485.6185076242015,
      "motor":{
        "motorType":"kde_direct_KDE600XF_530_G3"
      },
      "prop":{
        "propType":"apc_propellers_18_1x10"
      },
      "flange":{
        "offset":-27.280639910458927,
        "angle":0.0
      }
    },
    "rearSegment":{
      "node_type":"SidewaysBendWithTopSegment",
      "angle":-90.0,
      "armLength":197.58753093481337,
      "mainSegment":{
        "node_type":"PropArm",
        "armLength":140.46714199766052,
        "motor":{
          "motorType":"t_motor_P60KV340"
        },
        "prop":{
          "propType":"apc_propellers_13x8"
        },
        "flange":{
          "offset":-7.520184745439593,
          "angle":237.47390430893486
        }
      },
      "topSegment":{
        "node_type":"SidewaysBendSegment",
        "angle":-90.0,
        "armLength":254.77158518236703,
        "mainSegment":{
          "node_type":"AngledPropArm",
          "armLength":337.3731660648703,
          "motor":{
            "motorType":"kde_direct_KDE4012XF_400"
          },
          "prop":{
            "propType":"apc_propellers_15x6E"
          }
        }
      }
    },
    "rearCenterSegment":{
      "node_type":"AngledPropArm",
      "armLength":314.2589121571956,
      "motor":{
        "motorType":"t_motor_AT4130KV300"
      },
      "prop":{
        "propType":"apc_propellers_13x8"
      }
    }
  },
  "fuselageWithComponents":{
    "node_type":"SingleBatteryFuselageWithComponents",
    "battery":{
      "batteryType":"TurnigyGraphene1400mAh4S75C"
    },
    "fuselage":{
      "length":90.0,
      "vertDiameter":52.5,
      "horzDiameter":333.9,
      "floorHeight":8.75,
      "batteryX":0.0,
      "batteryY":6.0,
      "rpmX":0.0,
      "rpmY":-101.3,
      "autoPilotX":0.0,
      "autoPilotY":45.0,
      "currentX":0.0,
      "currentY":-81.15,
      "voltageX":0.0,
      "voltageY":98.8,
      "gpsX":0.0,
      "gpsY":-41.0,
      "varioX":0.0,
      "varioY":77.15
    }
  }
}