{
  "extra":{
    
  },
  "name":"design_18_16a05b76efdb4785b2da0e58831ee67b_dw",
  "parameters":[
    {
      "parameter_name":"Arm_4428_Length",
      "value":"442.9995426191446",
      "component_properties":[
        {
          "component_name":"Arm_4428_1",
          "component_property":"Length"
        }
      ],
      "optimization":"arm_length"
    },
    {
      "parameter_name":"Arm_4429_Length",
      "value":"313.54999496000454",
      "component_properties":[
        {
          "component_name":"Arm_4429_1",
          "component_property":"Length"
        },
        {
          "component_name":"Arm_4429_2",
          "component_property":"Length"
        }
      ],
      "optimization":"arm_length"
    },
    {
      "parameter_name":"Arm_4430_Length",
      "value":"438.41993747955564",
      "component_properties":[
        {
          "component_name":"Arm_4430_1",
          "component_property":"Length"
        },
        {
          "component_name":"Arm_4430_2",
          "component_property":"Length"
        }
      ],
      "optimization":"arm_length"
    },
    {
      "parameter_name":"Arm_4431_Length",
      "value":"287.32764946897214",
      "component_properties":[
        {
          "component_name":"Arm_4431_1",
          "component_property":"Length"
        }
      ],
      "optimization":"arm_length"
    },
    {
      "parameter_name":"Arm_4432_Length",
      "value":"113.4383014328688",
      "component_properties":[
        {
          "component_name":"Arm_4432_1",
          "component_property":"Length"
        }
      ],
      "optimization":"arm_length"
    },
    {
      "parameter_name":"BODY_ROT_ANGLE",
      "value":"0.0",
      "component_properties":[
        {
          "component_name":"Fuselage_1",
          "component_property":"BOTTOM_CONNECTOR_ROTATION"
        },
        {
          "component_name":"Orient",
          "component_property":"Z_ANGLE"
        }
      ]
    },
    {
      "parameter_name":"Bend_1_CLOCK_ANGLE",
      "value":"180.0",
      "component_properties":[
        {
          "component_name":"Bend_1",
          "component_property":"ANGHORZCONN"
        }
      ]
    },
    {
      "parameter_name":"Bend_2_CLOCK_ANGLE",
      "value":"180.0",
      "component_properties":[
        {
          "component_name":"Bend_2",
          "component_property":"ANGHORZCONN"
        }
      ]
    },
    {
      "parameter_name":"Bend_3_CLOCK_ANGLE",
      "value":"180.0",
      "component_properties":[
        {
          "component_name":"Bend_3",
          "component_property":"ANGHORZCONN"
        }
      ]
    },
    {
      "parameter_name":"Bend_4_CLOCK_ANGLE",
      "value":"180.0",
      "component_properties":[
        {
          "component_name":"Bend_4",
          "component_property":"ANGHORZCONN"
        }
      ]
    },
    {
      "parameter_name":"CargoCaseRotation",
      "value":"360.0",
      "component_properties":[
        {
          "component_name":"CargoCase",
          "component_property":"Rotation"
        }
      ]
    },
    {
      "parameter_name":"CargoMass",
      "value":"0.5",
      "component_properties":[
        {
          "component_name":"Cargo",
          "component_property":"WEIGHT"
        }
      ]
    },
    {
      "parameter_name":"ControlChannelAuto",
      "value":"-1",
      "component_properties":[
        {
          "component_name":"Motor_1",
          "component_property":"CONTROL_CHANNEL"
        },
        {
          "component_name":"Motor_2",
          "component_property":"CONTROL_CHANNEL"
        },
        {
          "component_name":"Motor_3",
          "component_property":"CONTROL_CHANNEL"
        },
        {
          "component_name":"Motor_4",
          "component_property":"CONTROL_CHANNEL"
        }
      ]
    },
    {
      "parameter_name":"FUSELAGE_AUTOPILOT_X_OFFSET",
      "value":"0.0",
      "component_properties":[
        {
          "component_name":"Fuselage_1",
          "component_property":"FLOOR_CONNECTOR_4_DISP_LENGTH"
        }
      ],
      "optimization":"fuselage_sensor_x"
    },
    {
      "parameter_name":"FUSELAGE_AUTOPILOT_Y_OFFSET",
      "value":"95.0",
      "component_properties":[
        {
          "component_name":"Fuselage_1",
          "component_property":"FLOOR_CONNECTOR_4_DISP_WIDTH"
        }
      ],
      "optimization":"fuselage_sensor_y"
    },
    {
      "parameter_name":"FUSELAGE_BATTERY1_X_OFFSET",
      "value":"0.0",
      "component_properties":[
        {
          "component_name":"Fuselage_1",
          "component_property":"FLOOR_CONNECTOR_1_DISP_LENGTH"
        }
      ],
      "optimization":"fuselage_battery_x"
    },
    {
      "parameter_name":"FUSELAGE_BATTERY1_Y_OFFSET",
      "value":"-27.0",
      "component_properties":[
        {
          "component_name":"Fuselage_1",
          "component_property":"FLOOR_CONNECTOR_1_DISP_WIDTH"
        }
      ],
      "optimization":"fuselage_battery_y"
    },
    {
      "parameter_name":"FUSELAGE_BATTERY2_X_OFFSET",
      "value":"0.0",
      "component_properties":[
        {
          "component_name":"Fuselage_1",
          "component_property":"FLOOR_CONNECTOR_2_DISP_LENGTH"
        }
      ],
      "optimization":"fuselage_battery_x"
    },
    {
      "parameter_name":"FUSELAGE_BATTERY2_Y_OFFSET",
      "value":"40.0",
      "component_properties":[
        {
          "component_name":"Fuselage_1",
          "component_property":"FLOOR_CONNECTOR_2_DISP_WIDTH"
        }
      ],
      "optimization":"fuselage_battery_y"
    },
    {
      "parameter_name":"FUSELAGE_CURRENT_X_OFFSET",
      "value":"0.0",
      "component_properties":[
        {
          "component_name":"Fuselage_1",
          "component_property":"FLOOR_CONNECTOR_5_DISP_LENGTH"
        }
      ],
      "optimization":"fuselage_sensor_x"
    },
    {
      "parameter_name":"FUSELAGE_CURRENT_Y_OFFSET",
      "value":"-131.15",
      "component_properties":[
        {
          "component_name":"Fuselage_1",
          "component_property":"FLOOR_CONNECTOR_5_DISP_WIDTH"
        }
      ],
      "optimization":"fuselage_sensor_y"
    },
    {
      "parameter_name":"FUSELAGE_FLOOR_HEIGHT",
      "value":"22.75",
      "component_properties":[
        {
          "component_name":"Fuselage_1",
          "component_property":"FLOOR_HEIGHT"
        }
      ],
      "optimization":"fuselage_floor_height"
    },
    {
      "parameter_name":"FUSELAGE_GPS_X_OFFSET",
      "value":"0.0",
      "component_properties":[
        {
          "component_name":"Fuselage_1",
          "component_property":"FLOOR_CONNECTOR_7_DISP_LENGTH"
        }
      ],
      "optimization":"fuselage_sensor_x"
    },
    {
      "parameter_name":"FUSELAGE_GPS_Y_OFFSET",
      "value":"-91.0",
      "component_properties":[
        {
          "component_name":"Fuselage_1",
          "component_property":"FLOOR_CONNECTOR_7_DISP_WIDTH"
        }
      ],
      "optimization":"fuselage_sensor_y"
    },
    {
      "parameter_name":"FUSELAGE_HORZ_DIAMETER",
      "value":"483.9",
      "component_properties":[
        {
          "component_name":"Fuselage_1",
          "component_property":"HORZ_DIAMETER"
        }
      ],
      "optimization":"fuselage_horz"
    },
    {
      "parameter_name":"FUSELAGE_LENGTH",
      "value":"207.0",
      "component_properties":[
        {
          "component_name":"Fuselage_1",
          "component_property":"FUSE_CYL_LENGTH"
        }
      ],
      "optimization":"fuselage_length"
    },
    {
      "parameter_name":"FUSELAGE_RPM_X_OFFSET",
      "value":"0.0",
      "component_properties":[
        {
          "component_name":"Fuselage_1",
          "component_property":"FLOOR_CONNECTOR_3_DISP_LENGTH"
        }
      ],
      "optimization":"fuselage_sensor_x"
    },
    {
      "parameter_name":"FUSELAGE_RPM_Y_OFFSET",
      "value":"-151.3",
      "component_properties":[
        {
          "component_name":"Fuselage_1",
          "component_property":"FLOOR_CONNECTOR_3_DISP_WIDTH"
        }
      ],
      "optimization":"fuselage_sensor_y"
    },
    {
      "parameter_name":"FUSELAGE_VARIO_X_OFFSET",
      "value":"0.0",
      "component_properties":[
        {
          "component_name":"Fuselage_1",
          "component_property":"FLOOR_CONNECTOR_8_DISP_LENGTH"
        }
      ],
      "optimization":"fuselage_sensor_x"
    },
    {
      "parameter_name":"FUSELAGE_VARIO_Y_OFFSET",
      "value":"127.15",
      "component_properties":[
        {
          "component_name":"Fuselage_1",
          "component_property":"FLOOR_CONNECTOR_8_DISP_WIDTH"
        }
      ],
      "optimization":"fuselage_sensor_y"
    },
    {
      "parameter_name":"FUSELAGE_VERT_DIAMETER",
      "value":"136.5",
      "component_properties":[
        {
          "component_name":"Fuselage_1",
          "component_property":"VERT_DIAMETER"
        }
      ],
      "optimization":"fuselage_vert"
    },
    {
      "parameter_name":"FUSELAGE_VOLTAGE_X_OFFSET",
      "value":"0.0",
      "component_properties":[
        {
          "component_name":"Fuselage_1",
          "component_property":"FLOOR_CONNECTOR_6_DISP_LENGTH"
        }
      ],
      "optimization":"fuselage_sensor_x"
    },
    {
      "parameter_name":"FUSELAGE_VOLTAGE_Y_OFFSET",
      "value":"148.8",
      "component_properties":[
        {
          "component_name":"Fuselage_1",
          "component_property":"FLOOR_CONNECTOR_6_DISP_WIDTH"
        }
      ],
      "optimization":"fuselage_sensor_y"
    },
    {
      "parameter_name":"Flange_1426_1_CLOCK_ANGLE",
      "value":"0.0",
      "component_properties":[
        {
          "component_name":"Flange_1426_1",
          "component_property":"SIDE_ANGLE"
        }
      ]
    },
    {
      "parameter_name":"Flange_1426_2_CLOCK_ANGLE",
      "value":"360.0",
      "component_properties":[
        {
          "component_name":"Flange_1426_2",
          "component_property":"SIDE_ANGLE"
        }
      ]
    },
    {
      "parameter_name":"NACA_2506_THICKNESS",
      "value":"6",
      "component_properties":[
        {
          "component_name":"Wing_526_1",
          "component_property":"THICKNESS"
        },
        {
          "component_name":"Wing_526_2",
          "component_property":"THICKNESS"
        }
      ]
    },
    {
      "parameter_name":"NegPropDir",
      "value":"-1",
      "component_properties":[
        {
          "component_name":"Propeller_1",
          "component_property":"Direction"
        },
        {
          "component_name":"Propeller_2",
          "component_property":"Direction"
        },
        {
          "component_name":"Propeller_3",
          "component_property":"Direction"
        }
      ]
    },
    {
      "parameter_name":"NegPropType",
      "value":"-1",
      "component_properties":[
        {
          "component_name":"Propeller_1",
          "component_property":"Prop_type"
        },
        {
          "component_name":"Propeller_2",
          "component_property":"Prop_type"
        }
      ]
    },
    {
      "parameter_name":"PosPropDir",
      "value":"1",
      "component_properties":[
        {
          "component_name":"Propeller_4",
          "component_property":"Direction"
        }
      ]
    },
    {
      "parameter_name":"PosPropType",
      "value":"1",
      "component_properties":[
        {
          "component_name":"Propeller_3",
          "component_property":"Prop_type"
        },
        {
          "component_name":"Propeller_4",
          "component_property":"Prop_type"
        }
      ]
    },
    {
      "parameter_name":"RotatedArm_1567_1_ROT2",
      "value":"0.0",
      "component_properties":[
        {
          "component_name":"RotatedArm_1567_1",
          "component_property":"END_ROT"
        }
      ]
    },
    {
      "parameter_name":"RotatedArm_1567_Length",
      "value":"327.18301390161736",
      "component_properties":[
        {
          "component_name":"RotatedArm_1567_1",
          "component_property":"Length"
        }
      ],
      "optimization":"arm_length"
    },
    {
      "parameter_name":"RotatedArm_1568_1_ROT2",
      "value":"0.0",
      "component_properties":[
        {
          "component_name":"RotatedArm_1568_1",
          "component_property":"END_ROT"
        }
      ]
    },
    {
      "parameter_name":"RotatedArm_1568_Length",
      "value":"50.0",
      "component_properties":[
        {
          "component_name":"RotatedArm_1568_1",
          "component_property":"Length"
        }
      ],
      "optimization":"arm_length"
    },
    {
      "parameter_name":"RotatedArm_1569_1_ROT2",
      "value":"0.0",
      "component_properties":[
        {
          "component_name":"RotatedArm_1569_1",
          "component_property":"END_ROT"
        }
      ]
    },
    {
      "parameter_name":"RotatedArm_1569_Length",
      "value":"92.60521001239921",
      "component_properties":[
        {
          "component_name":"RotatedArm_1569_1",
          "component_property":"Length"
        }
      ],
      "optimization":"arm_length"
    },
    {
      "parameter_name":"RotatedArm_1570_1_ROT2",
      "value":"0.0",
      "component_properties":[
        {
          "component_name":"RotatedArm_1570_1",
          "component_property":"END_ROT"
        }
      ]
    },
    {
      "parameter_name":"RotatedArm_1570_Length",
      "value":"50.0",
      "component_properties":[
        {
          "component_name":"RotatedArm_1570_1",
          "component_property":"Length"
        }
      ],
      "optimization":"arm_length"
    },
    {
      "parameter_name":"Wing_526_1_TUBE_OFFSET",
      "value":"143.6661436844159",
      "component_properties":[
        {
          "component_name":"Wing_526_1",
          "component_property":"TUBE_OFFSET"
        }
      ]
    },
    {
      "parameter_name":"Wing_526_1_TUBE_ROT",
      "value":"48.98772443190262",
      "component_properties":[
        {
          "component_name":"Wing_526_1",
          "component_property":"TUBE_ROTATION"
        }
      ]
    },
    {
      "parameter_name":"Wing_526_2_TUBE_OFFSET",
      "value":"60.43038242590944",
      "component_properties":[
        {
          "component_name":"Wing_526_2",
          "component_property":"TUBE_OFFSET"
        }
      ]
    },
    {
      "parameter_name":"Wing_526_2_TUBE_ROT",
      "value":"311.0122755680974",
      "component_properties":[
        {
          "component_name":"Wing_526_2",
          "component_property":"TUBE_ROTATION"
        }
      ]
    },
    {
      "parameter_name":"Wing_526_AILERON_BIAS",
      "value":"0.4230828695140618",
      "component_properties":[
        {
          "component_name":"Wing_526_1",
          "component_property":"AILERON_BIAS"
        },
        {
          "component_name":"Wing_526_2",
          "component_property":"AILERON_BIAS"
        }
      ],
      "optimization":"wing_aileron_bias"
    },
    {
      "parameter_name":"Wing_526_CHORD_INNER",
      "value":"350.21074962463706",
      "component_properties":[
        {
          "component_name":"Wing_526_1",
          "component_property":"CHORD_1"
        },
        {
          "component_name":"Wing_526_2",
          "component_property":"CHORD_2"
        }
      ],
      "optimization":"wing_chord_inner"
    },
    {
      "parameter_name":"Wing_526_CHORD_OUTER",
      "value":"194.0067963494414",
      "component_properties":[
        {
          "component_name":"Wing_526_1",
          "component_property":"CHORD_2"
        },
        {
          "component_name":"Wing_526_2",
          "component_property":"CHORD_1"
        }
      ],
      "optimization":"wing_chord_outer"
    },
    {
      "parameter_name":"Wing_526_FLAP_BIAS",
      "value":"0.5993259100181745",
      "component_properties":[
        {
          "component_name":"Wing_526_1",
          "component_property":"FLAP_BIAS"
        },
        {
          "component_name":"Wing_526_2",
          "component_property":"FLAP_BIAS"
        }
      ],
      "optimization":"wing_flap_bias"
    },
    {
      "parameter_name":"Wing_526_LOAD",
      "value":"882.1124331302683",
      "component_properties":[
        {
          "component_name":"Wing_526_1",
          "component_property":"LOAD"
        },
        {
          "component_name":"Wing_526_2",
          "component_property":"LOAD"
        }
      ],
      "optimization":"wing_load"
    },
    {
      "parameter_name":"Wing_526_NACA_Profile",
      "value":"2506",
      "component_properties":[
        {
          "component_name":"Wing_526_1",
          "component_property":"NACA_Profile"
        },
        {
          "component_name":"Wing_526_2",
          "component_property":"NACA_Profile"
        }
      ]
    },
    {
      "parameter_name":"Wing_526_SPAN",
      "value":"204.09652611032536",
      "component_properties":[
        {
          "component_name":"Wing_526_1",
          "component_property":"SPAN"
        },
        {
          "component_name":"Wing_526_2",
          "component_property":"SPAN"
        }
      ],
      "optimization":"wing_span"
    },
    {
      "parameter_name":"Wing_526_TAPER_OFFSET",
      "value":"1",
      "component_properties":[
        {
          "component_name":"Wing_526_1",
          "component_property":"TAPER_OFFSET"
        },
        {
          "component_name":"Wing_526_2",
          "component_property":"TAPER_OFFSET"
        }
      ]
    }
  ],
  "components":[
    {
      "component_instance":"Arm_4428_1",
      "component_type":"Tube",
      "component_choice":"0394OD_para_tube"
    },
    {
      "component_instance":"Arm_4429_1",
      "component_type":"Tube",
      "component_choice":"0394OD_para_tube"
    },
    {
      "component_instance":"Arm_4429_2",
      "component_type":"Tube",
      "component_choice":"0394OD_para_tube"
    },
    {
      "component_instance":"Arm_4430_1",
      "component_type":"Tube",
      "component_choice":"0394OD_para_tube"
    },
    {
      "component_instance":"Arm_4430_2",
      "component_type":"Tube",
      "component_choice":"0394OD_para_tube"
    },
    {
      "component_instance":"Arm_4431_1",
      "component_type":"Tube",
      "component_choice":"0394OD_para_tube"
    },
    {
      "component_instance":"Arm_4432_1",
      "component_type":"Tube",
      "component_choice":"0394OD_para_tube"
    },
    {
      "component_instance":"BatteryController_2701_1",
      "component_type":"BatteryController",
      "component_choice":"BatteryController"
    },
    {
      "component_instance":"Battery_1",
      "component_type":"Battery",
      "component_choice":"Tattu10C25000mAh6S1PHV"
    },
    {
      "component_instance":"Battery_2",
      "component_type":"Battery",
      "component_choice":"Tattu10C25000mAh6S1PHV"
    },
    {
      "component_instance":"Bend_1",
      "component_type":"Para_Hub_2",
      "component_choice":"0394od_para_hub_2"
    },
    {
      "component_instance":"Bend_2",
      "component_type":"Para_Hub_2",
      "component_choice":"0394od_para_hub_2"
    },
    {
      "component_instance":"Bend_3",
      "component_type":"Para_Hub_2",
      "component_choice":"0394od_para_hub_2"
    },
    {
      "component_instance":"Bend_4",
      "component_type":"Para_Hub_2",
      "component_choice":"0394od_para_hub_2"
    },
    {
      "component_instance":"Cargo",
      "component_type":"Cargo",
      "component_choice":"Cargo"
    },
    {
      "component_instance":"CargoCase",
      "component_type":"CargoCase",
      "component_choice":"CargoCase"
    },
    {
      "component_instance":"Cross_1",
      "component_type":"Para_Hub_4",
      "component_choice":"0394od_para_hub_4"
    },
    {
      "component_instance":"Flange_1",
      "component_type":"Flange",
      "component_choice":"0394_para_flange"
    },
    {
      "component_instance":"Flange_1426_1",
      "component_type":"Flange",
      "component_choice":"0394_para_flange"
    },
    {
      "component_instance":"Flange_1426_2",
      "component_type":"Flange",
      "component_choice":"0394_para_flange"
    },
    {
      "component_instance":"Flange_2",
      "component_type":"Flange",
      "component_choice":"0394_para_flange"
    },
    {
      "component_instance":"Fuselage_1",
      "component_type":"UAV_Fuselage",
      "component_choice":"capsule_fuselage"
    },
    {
      "component_instance":"MainHub_1",
      "component_type":"Para_Hub_4",
      "component_choice":"0394od_para_hub_4"
    },
    {
      "component_instance":"Motor_1",
      "component_type":"Motor",
      "component_choice":"t_motor_MN4012KV480"
    },
    {
      "component_instance":"Motor_2",
      "component_type":"Motor",
      "component_choice":"kde_direct_KDE4012XF_400"
    },
    {
      "component_instance":"Motor_3",
      "component_type":"Motor",
      "component_choice":"t_motor_MN5212KV420"
    },
    {
      "component_instance":"Motor_4",
      "component_type":"Motor",
      "component_choice":"kde_direct_KDE4012XF_400"
    },
    {
      "component_instance":"Orient",
      "component_type":"Orient",
      "component_choice":"Orient"
    },
    {
      "component_instance":"Propeller_1",
      "component_type":"Propeller",
      "component_choice":"apc_propellers_17x8N"
    },
    {
      "component_instance":"Propeller_2",
      "component_type":"Propeller",
      "component_choice":"apc_propellers_15x4W"
    },
    {
      "component_instance":"Propeller_3",
      "component_type":"Propeller",
      "component_choice":"apc_propellers_17x6"
    },
    {
      "component_instance":"Propeller_4",
      "component_type":"Propeller",
      "component_choice":"apc_propellers_15x4W"
    },
    {
      "component_instance":"RotatedArm_1567_1",
      "component_type":"Tube",
      "component_choice":"0394OD_para_tube"
    },
    {
      "component_instance":"RotatedArm_1568_1",
      "component_type":"Tube",
      "component_choice":"0394OD_para_tube"
    },
    {
      "component_instance":"RotatedArm_1569_1",
      "component_type":"Tube",
      "component_choice":"0394OD_para_tube"
    },
    {
      "component_instance":"RotatedArm_1570_1",
      "component_type":"Tube",
      "component_choice":"0394OD_para_tube"
    },
    {
      "component_instance":"Sensor_1",
      "component_type":"Sensor",
      "component_choice":"RpmTemp"
    },
    {
      "component_instance":"Sensor_2",
      "component_type":"Sensor",
      "component_choice":"Autopilot"
    },
    {
      "component_instance":"Sensor_3",
      "component_type":"Sensor",
      "component_choice":"Current"
    },
    {
      "component_instance":"Sensor_4",
      "component_type":"Sensor",
      "component_choice":"Voltage"
    },
    {
      "component_instance":"Sensor_5",
      "component_type":"Sensor",
      "component_choice":"GPS"
    },
    {
      "component_instance":"Sensor_6",
      "component_type":"Sensor",
      "component_choice":"Variometer"
    },
    {
      "component_instance":"Servo_1",
      "component_type":"Servo",
      "component_choice":"Hitec_HS_81"
    },
    {
      "component_instance":"Servo_2",
      "component_type":"Servo",
      "component_choice":"Hitec_HS_81"
    },
    {
      "component_instance":"Wing_526_1",
      "component_type":"Wing",
      "component_choice":"Wing_vert_hole"
    },
    {
      "component_instance":"Wing_526_2",
      "component_type":"Wing",
      "component_choice":"Wing_vert_hole"
    }
  ],
  "connections":[
    {
      "from_ci":"Arm_4428_1",
      "from_conn":"EndConnection",
      "to_ci":"Flange_1",
      "to_conn":"BottomConnector"
    },
    {
      "from_ci":"Arm_4429_1",
      "from_conn":"EndConnection",
      "to_ci":"Flange_1426_1",
      "to_conn":"SideConnector"
    },
    {
      "from_ci":"Arm_4429_2",
      "from_conn":"EndConnection",
      "to_ci":"Flange_1426_2",
      "to_conn":"SideConnector"
    },
    {
      "from_ci":"Arm_4430_1",
      "from_conn":"EndConnection",
      "to_ci":"Wing_526_1",
      "to_conn":"Wing_Tube_Connector"
    },
    {
      "from_ci":"Arm_4430_2",
      "from_conn":"EndConnection",
      "to_ci":"Wing_526_2",
      "to_conn":"Wing_Tube_Connector"
    },
    {
      "from_ci":"Arm_4431_1",
      "from_conn":"EndConnection",
      "to_ci":"Flange_2",
      "to_conn":"BottomConnector"
    },
    {
      "from_ci":"Arm_4432_1",
      "from_conn":"EndConnection",
      "to_ci":"Cross_1",
      "to_conn":"Side_Connector_3"
    },
    {
      "from_ci":"BatteryController_2701_1",
      "from_conn":"MotorPower",
      "to_ci":"Motor_2",
      "to_conn":"MotorPower"
    },
    {
      "from_ci":"BatteryController_2701_1",
      "from_conn":"MotorPower",
      "to_ci":"Motor_1",
      "to_conn":"MotorPower"
    },
    {
      "from_ci":"BatteryController_2701_1",
      "from_conn":"MotorPower",
      "to_ci":"Motor_4",
      "to_conn":"MotorPower"
    },
    {
      "from_ci":"BatteryController_2701_1",
      "from_conn":"MotorPower",
      "to_ci":"Motor_3",
      "to_conn":"MotorPower"
    },
    {
      "from_ci":"Battery_1",
      "from_conn":"PowerBus",
      "to_ci":"BatteryController_2701_1",
      "to_conn":"BatteryPower"
    },
    {
      "from_ci":"Battery_1",
      "from_conn":"PowerBus",
      "to_ci":"Battery_2",
      "to_conn":"PowerBus"
    },
    {
      "from_ci":"Bend_1",
      "from_conn":"Side_Connector_2",
      "to_ci":"RotatedArm_1570_1",
      "to_conn":"BaseConnection"
    },
    {
      "from_ci":"Bend_2",
      "from_conn":"Side_Connector_2",
      "to_ci":"RotatedArm_1567_1",
      "to_conn":"BaseConnection"
    },
    {
      "from_ci":"Bend_3",
      "from_conn":"Side_Connector_2",
      "to_ci":"RotatedArm_1568_1",
      "to_conn":"BaseConnection"
    },
    {
      "from_ci":"Bend_4",
      "from_conn":"Side_Connector_2",
      "to_ci":"Arm_4431_1",
      "to_conn":"BaseConnection"
    },
    {
      "from_ci":"CargoCase",
      "from_conn":"CargoConnector",
      "to_ci":"Cargo",
      "to_conn":"CargoConnector"
    },
    {
      "from_ci":"Cross_1",
      "from_conn":"Side_Connector_2",
      "to_ci":"Arm_4430_2",
      "to_conn":"BaseConnection"
    },
    {
      "from_ci":"Cross_1",
      "from_conn":"Side_Connector_1",
      "to_ci":"RotatedArm_1569_1",
      "to_conn":"BaseConnection"
    },
    {
      "from_ci":"Cross_1",
      "from_conn":"Side_Connector_4",
      "to_ci":"Arm_4430_1",
      "to_conn":"BaseConnection"
    },
    {
      "from_ci":"Flange_1",
      "from_conn":"TopConnector",
      "to_ci":"Motor_1",
      "to_conn":"Base_Connector"
    },
    {
      "from_ci":"Flange_1426_1",
      "from_conn":"TopConnector",
      "to_ci":"Motor_2",
      "to_conn":"Base_Connector"
    },
    {
      "from_ci":"Flange_1426_2",
      "from_conn":"TopConnector",
      "to_ci":"Motor_4",
      "to_conn":"Base_Connector"
    },
    {
      "from_ci":"Flange_2",
      "from_conn":"TopConnector",
      "to_ci":"Motor_3",
      "to_conn":"Base_Connector"
    },
    {
      "from_ci":"Fuselage_1",
      "from_conn":"FloorConnector5",
      "to_ci":"Sensor_3",
      "to_conn":"SensorConnector"
    },
    {
      "from_ci":"Fuselage_1",
      "from_conn":"FloorConnector4",
      "to_ci":"Sensor_2",
      "to_conn":"SensorConnector"
    },
    {
      "from_ci":"Fuselage_1",
      "from_conn":"FloorConnector3",
      "to_ci":"Sensor_1",
      "to_conn":"SensorConnector"
    },
    {
      "from_ci":"Fuselage_1",
      "from_conn":"FloorConnector2",
      "to_ci":"Battery_2",
      "to_conn":"Bottom_Connector"
    },
    {
      "from_ci":"Fuselage_1",
      "from_conn":"FloorConnector1",
      "to_ci":"Battery_1",
      "to_conn":"Bottom_Connector"
    },
    {
      "from_ci":"Fuselage_1",
      "from_conn":"FloorConnector6",
      "to_ci":"Sensor_4",
      "to_conn":"SensorConnector"
    },
    {
      "from_ci":"Fuselage_1",
      "from_conn":"BottomConnector",
      "to_ci":"MainHub_1",
      "to_conn":"Top_Connector"
    },
    {
      "from_ci":"Fuselage_1",
      "from_conn":"FloorConnector7",
      "to_ci":"Sensor_5",
      "to_conn":"SensorConnector"
    },
    {
      "from_ci":"Fuselage_1",
      "from_conn":"FloorConnector8",
      "to_ci":"Sensor_6",
      "to_conn":"SensorConnector"
    },
    {
      "from_ci":"MainHub_1",
      "from_conn":"Side_Connector_4",
      "to_ci":"Arm_4429_2",
      "to_conn":"BaseConnection"
    },
    {
      "from_ci":"MainHub_1",
      "from_conn":"Bottom_Connector",
      "to_ci":"CargoCase",
      "to_conn":"Case2HubConnector"
    },
    {
      "from_ci":"MainHub_1",
      "from_conn":"Side_Connector_1",
      "to_ci":"Arm_4432_1",
      "to_conn":"BaseConnection"
    },
    {
      "from_ci":"MainHub_1",
      "from_conn":"Side_Connector_2",
      "to_ci":"Arm_4429_1",
      "to_conn":"BaseConnection"
    },
    {
      "from_ci":"MainHub_1",
      "from_conn":"Side_Connector_3",
      "to_ci":"Arm_4428_1",
      "to_conn":"BaseConnection"
    },
    {
      "from_ci":"Motor_1",
      "from_conn":"Prop_Connector",
      "to_ci":"Propeller_1",
      "to_conn":"MOTOR_CONNECTOR_CS_IN"
    },
    {
      "from_ci":"Motor_2",
      "from_conn":"Prop_Connector",
      "to_ci":"Propeller_2",
      "to_conn":"MOTOR_CONNECTOR_CS_IN"
    },
    {
      "from_ci":"Motor_3",
      "from_conn":"Prop_Connector",
      "to_ci":"Propeller_3",
      "to_conn":"MOTOR_CONNECTOR_CS_IN"
    },
    {
      "from_ci":"Motor_4",
      "from_conn":"Prop_Connector",
      "to_ci":"Propeller_4",
      "to_conn":"MOTOR_CONNECTOR_CS_IN"
    },
    {
      "from_ci":"Orient",
      "from_conn":"ORIENTCONN",
      "to_ci":"MainHub_1",
      "to_conn":"Orient_Connector"
    },
    {
      "from_ci":"RotatedArm_1567_1",
      "from_conn":"EndConnection",
      "to_ci":"Bend_3",
      "to_conn":"Side_Connector_1"
    },
    {
      "from_ci":"RotatedArm_1568_1",
      "from_conn":"EndConnection",
      "to_ci":"Bend_4",
      "to_conn":"Side_Connector_1"
    },
    {
      "from_ci":"RotatedArm_1569_1",
      "from_conn":"EndConnection",
      "to_ci":"Bend_1",
      "to_conn":"Side_Connector_1"
    },
    {
      "from_ci":"RotatedArm_1570_1",
      "from_conn":"EndConnection",
      "to_ci":"Bend_2",
      "to_conn":"Side_Connector_1"
    },
    {
      "from_ci":"Wing_526_1",
      "from_conn":"Wing_Servo_Connector",
      "to_ci":"Servo_1",
      "to_conn":"Connector"
    },
    {
      "from_ci":"Wing_526_2",
      "from_conn":"Wing_Servo_Connector",
      "to_ci":"Servo_2",
      "to_conn":"Connector"
    },
    {
      "from_ci":"Flange_1",
      "from_conn":"BottomConnector",
      "to_ci":"Arm_4428_1",
      "to_conn":"EndConnection"
    },
    {
      "from_ci":"Flange_1426_1",
      "from_conn":"SideConnector",
      "to_ci":"Arm_4429_1",
      "to_conn":"EndConnection"
    },
    {
      "from_ci":"Flange_1426_2",
      "from_conn":"SideConnector",
      "to_ci":"Arm_4429_2",
      "to_conn":"EndConnection"
    },
    {
      "from_ci":"Wing_526_1",
      "from_conn":"Wing_Tube_Connector",
      "to_ci":"Arm_4430_1",
      "to_conn":"EndConnection"
    },
    {
      "from_ci":"Wing_526_2",
      "from_conn":"Wing_Tube_Connector",
      "to_ci":"Arm_4430_2",
      "to_conn":"EndConnection"
    },
    {
      "from_ci":"Flange_2",
      "from_conn":"BottomConnector",
      "to_ci":"Arm_4431_1",
      "to_conn":"EndConnection"
    },
    {
      "from_ci":"Cross_1",
      "from_conn":"Side_Connector_3",
      "to_ci":"Arm_4432_1",
      "to_conn":"EndConnection"
    },
    {
      "from_ci":"Motor_2",
      "from_conn":"MotorPower",
      "to_ci":"BatteryController_2701_1",
      "to_conn":"MotorPower"
    },
    {
      "from_ci":"Motor_1",
      "from_conn":"MotorPower",
      "to_ci":"BatteryController_2701_1",
      "to_conn":"MotorPower"
    },
    {
      "from_ci":"Motor_4",
      "from_conn":"MotorPower",
      "to_ci":"BatteryController_2701_1",
      "to_conn":"MotorPower"
    },
    {
      "from_ci":"Motor_3",
      "from_conn":"MotorPower",
      "to_ci":"BatteryController_2701_1",
      "to_conn":"MotorPower"
    },
    {
      "from_ci":"BatteryController_2701_1",
      "from_conn":"BatteryPower",
      "to_ci":"Battery_1",
      "to_conn":"PowerBus"
    },
    {
      "from_ci":"Battery_2",
      "from_conn":"PowerBus",
      "to_ci":"Battery_1",
      "to_conn":"PowerBus"
    },
    {
      "from_ci":"RotatedArm_1570_1",
      "from_conn":"BaseConnection",
      "to_ci":"Bend_1",
      "to_conn":"Side_Connector_2"
    },
    {
      "from_ci":"RotatedArm_1567_1",
      "from_conn":"BaseConnection",
      "to_ci":"Bend_2",
      "to_conn":"Side_Connector_2"
    },
    {
      "from_ci":"RotatedArm_1568_1",
      "from_conn":"BaseConnection",
      "to_ci":"Bend_3",
      "to_conn":"Side_Connector_2"
    },
    {
      "from_ci":"Arm_4431_1",
      "from_conn":"BaseConnection",
      "to_ci":"Bend_4",
      "to_conn":"Side_Connector_2"
    },
    {
      "from_ci":"Cargo",
      "from_conn":"CargoConnector",
      "to_ci":"CargoCase",
      "to_conn":"CargoConnector"
    },
    {
      "from_ci":"Arm_4430_2",
      "from_conn":"BaseConnection",
      "to_ci":"Cross_1",
      "to_conn":"Side_Connector_2"
    },
    {
      "from_ci":"RotatedArm_1569_1",
      "from_conn":"BaseConnection",
      "to_ci":"Cross_1",
      "to_conn":"Side_Connector_1"
    },
    {
      "from_ci":"Arm_4430_1",
      "from_conn":"BaseConnection",
      "to_ci":"Cross_1",
      "to_conn":"Side_Connector_4"
    },
    {
      "from_ci":"Motor_1",
      "from_conn":"Base_Connector",
      "to_ci":"Flange_1",
      "to_conn":"TopConnector"
    },
    {
      "from_ci":"Motor_2",
      "from_conn":"Base_Connector",
      "to_ci":"Flange_1426_1",
      "to_conn":"TopConnector"
    },
    {
      "from_ci":"Motor_4",
      "from_conn":"Base_Connector",
      "to_ci":"Flange_1426_2",
      "to_conn":"TopConnector"
    },
    {
      "from_ci":"Motor_3",
      "from_conn":"Base_Connector",
      "to_ci":"Flange_2",
      "to_conn":"TopConnector"
    },
    {
      "from_ci":"Sensor_3",
      "from_conn":"SensorConnector",
      "to_ci":"Fuselage_1",
      "to_conn":"FloorConnector5"
    },
    {
      "from_ci":"Sensor_2",
      "from_conn":"SensorConnector",
      "to_ci":"Fuselage_1",
      "to_conn":"FloorConnector4"
    },
    {
      "from_ci":"Sensor_1",
      "from_conn":"SensorConnector",
      "to_ci":"Fuselage_1",
      "to_conn":"FloorConnector3"
    },
    {
      "from_ci":"Battery_2",
      "from_conn":"Bottom_Connector",
      "to_ci":"Fuselage_1",
      "to_conn":"FloorConnector2"
    },
    {
      "from_ci":"Battery_1",
      "from_conn":"Bottom_Connector",
      "to_ci":"Fuselage_1",
      "to_conn":"FloorConnector1"
    },
    {
      "from_ci":"Sensor_4",
      "from_conn":"SensorConnector",
      "to_ci":"Fuselage_1",
      "to_conn":"FloorConnector6"
    },
    {
      "from_ci":"MainHub_1",
      "from_conn":"Top_Connector",
      "to_ci":"Fuselage_1",
      "to_conn":"BottomConnector"
    },
    {
      "from_ci":"Sensor_5",
      "from_conn":"SensorConnector",
      "to_ci":"Fuselage_1",
      "to_conn":"FloorConnector7"
    },
    {
      "from_ci":"Sensor_6",
      "from_conn":"SensorConnector",
      "to_ci":"Fuselage_1",
      "to_conn":"FloorConnector8"
    },
    {
      "from_ci":"Arm_4429_2",
      "from_conn":"BaseConnection",
      "to_ci":"MainHub_1",
      "to_conn":"Side_Connector_4"
    },
    {
      "from_ci":"CargoCase",
      "from_conn":"Case2HubConnector",
      "to_ci":"MainHub_1",
      "to_conn":"Bottom_Connector"
    },
    {
      "from_ci":"Arm_4432_1",
      "from_conn":"BaseConnection",
      "to_ci":"MainHub_1",
      "to_conn":"Side_Connector_1"
    },
    {
      "from_ci":"Arm_4429_1",
      "from_conn":"BaseConnection",
      "to_ci":"MainHub_1",
      "to_conn":"Side_Connector_2"
    },
    {
      "from_ci":"Arm_4428_1",
      "from_conn":"BaseConnection",
      "to_ci":"MainHub_1",
      "to_conn":"Side_Connector_3"
    },
    {
      "from_ci":"Propeller_1",
      "from_conn":"MOTOR_CONNECTOR_CS_IN",
      "to_ci":"Motor_1",
      "to_conn":"Prop_Connector"
    },
    {
      "from_ci":"Propeller_2",
      "from_conn":"MOTOR_CONNECTOR_CS_IN",
      "to_ci":"Motor_2",
      "to_conn":"Prop_Connector"
    },
    {
      "from_ci":"Propeller_3",
      "from_conn":"MOTOR_CONNECTOR_CS_IN",
      "to_ci":"Motor_3",
      "to_conn":"Prop_Connector"
    },
    {
      "from_ci":"Propeller_4",
      "from_conn":"MOTOR_CONNECTOR_CS_IN",
      "to_ci":"Motor_4",
      "to_conn":"Prop_Connector"
    },
    {
      "from_ci":"MainHub_1",
      "from_conn":"Orient_Connector",
      "to_ci":"Orient",
      "to_conn":"ORIENTCONN"
    },
    {
      "from_ci":"Bend_3",
      "from_conn":"Side_Connector_1",
      "to_ci":"RotatedArm_1567_1",
      "to_conn":"EndConnection"
    },
    {
      "from_ci":"Bend_4",
      "from_conn":"Side_Connector_1",
      "to_ci":"RotatedArm_1568_1",
      "to_conn":"EndConnection"
    },
    {
      "from_ci":"Bend_1",
      "from_conn":"Side_Connector_1",
      "to_ci":"RotatedArm_1569_1",
      "to_conn":"EndConnection"
    },
    {
      "from_ci":"Bend_2",
      "from_conn":"Side_Connector_1",
      "to_ci":"RotatedArm_1570_1",
      "to_conn":"EndConnection"
    },
    {
      "from_ci":"Servo_1",
      "from_conn":"Connector",
      "to_ci":"Wing_526_1",
      "to_conn":"Wing_Servo_Connector"
    },
    {
      "from_ci":"Servo_2",
      "from_conn":"Connector",
      "to_ci":"Wing_526_2",
      "to_conn":"Wing_Servo_Connector"
    }
  ]
}