{
  "generator_version":"UAV2_gen12",
  "name":"design_37694_637a302909064634ae836fbb26565541_s",
  "hub":{
    "node_type":"ConnectedHub6_2_2_2",
    "frontSegment":{
      "node_type":"PropArm",
      "armLength":493.8459961230738,
      "motor":{
        "motorType":"t_motor_AT4120KV500"
      },
      "prop":{
        "propType":"apc_propellers_16x6E"
      },
      "flange":{
        "offset":29.746717997030686,
        "angle":0.0
      }
    },
    "middleSegment":{
      "node_type":"PropArm",
      "armLength":387.8739583081344,
      "motor":{
        "motorType":"t_motor_MN5212KV420"
      },
      "prop":{
        "propType":"apc_propellers_18x8W"
      },
      "flange":{
        "offset":49.34417815252304,
        "angle":0.0
      }
    },
    "rearSegment":{
      "node_type":"AngledWingArm",
      "arm1Length":252.93843443914741,
      "arm2Length":198.99493372998433,
      "wing":{
        "wingType":"Wing_horiz_hole",
        "nacaProfile":"0021",
        "span":965.7263579293843,
        "chordInner":127.10993439371364,
        "chordOuter":172.01008504941802,
        "taperOffset":true,
        "aileronBias":0.35317743686755887,
        "flapBias":0.8653442485316978,
        "load":519.5563279985772,
        "tubeOffset":75.59353536604554,
        "tubeRot":252.580411737519
      },
      "servo":{
        "servoType":"Hitec_HS_225BB"
      }
    }
  },
  "fuselageWithComponents":{
    "node_type":"SingleBatteryFuselageWithComponents",
    "battery":{
      "batteryType":"TurnigyGraphene1200mAh6S75C"
    },
    "fuselage":{
      "length":84.0,
      "vertDiameter":52.5,
      "horzDiameter":353.4,
      "floorHeight":8.75,
      "batteryX":-4.5,
      "batteryY":6.0,
      "rpmX":-4.5,
      "rpmY":-107.8,
      "autoPilotX":-4.5,
      "autoPilotY":51.5,
      "currentX":-4.5,
      "currentY":-87.65,
      "voltageX":-4.5,
      "voltageY":105.3,
      "gpsX":-4.5,
      "gpsY":-47.5,
      "varioX":-4.5,
      "varioY":83.65
    }
  }
}