{
  "generator_version":"UAV2_gen12",
  "name":"design_40885_14900b624c0f44b4bb5d03c951342463_s",
  "hub":{
    "node_type":"ConnectedHub6_1_2_2_1",
    "frontCenterSegment":{
      "node_type":"AngledPropArm",
      "armLength":354.580442475002,
      "motor":{
        "motorType":"t_motor_AntigravityMN6007IIKV320"
      },
      "prop":{
        "propType":"apc_propellers_13x4_7SF"
      }
    },
    "frontSegment":{
      "node_type":"PropArm",
      "armLength":301.47924339637234,
      "motor":{
        "motorType":"t_motor_MN5212KV420"
      },
      "prop":{
        "propType":"apc_propellers_20x8E"
      },
      "flange":{
        "offset":-25.655515865310175,
        "angle":345.84510737824104
      }
    },
    "rearSegment":{
      "node_type":"PropArm",
      "armLength":478.40184274230074,
      "motor":{
        "motorType":"t_motor_AT4125KV540"
      },
      "prop":{
        "propType":"apc_propellers_17x6"
      },
      "flange":{
        "offset":13.524767381323613,
        "angle":0.0
      }
    },
    "rearCenterSegment":{
      "node_type":"AngledPropArm",
      "armLength":260.92938453934335,
      "motor":{
        "motorType":"kde_direct_KDE700XF_455_G3"
      },
      "prop":{
        "propType":"apc_propellers_15x7E"
      }
    }
  },
  "fuselageWithComponents":{
    "node_type":"SingleBatteryFuselageWithComponents",
    "battery":{
      "batteryType":"TurnigyGraphene6000mAh3S75C"
    },
    "fuselage":{
      "length":168.0,
      "vertDiameter":103.5,
      "horzDiameter":326.4,
      "floorHeight":17.25,
      "batteryX":0.0,
      "batteryY":6.0,
      "rpmX":0.0,
      "rpmY":-98.8,
      "autoPilotX":0.0,
      "autoPilotY":42.5,
      "currentX":0.0,
      "currentY":-78.65,
      "voltageX":0.0,
      "voltageY":96.3,
      "gpsX":0.0,
      "gpsY":-38.5,
      "varioX":0.0,
      "varioY":74.65
    }
  }
}