{
  "generator_version":"UAV2_gen12",
  "name":"design_47535_ac95b8f1026b4bff9a4cb39d43772d60_s",
  "hub":{
    "node_type":"ConnectedHub4_1_2_1",
    "frontSegment":{
      "node_type":"DoubleBendSegment",
      "angle":-90.0,
      "arm1Length":453.97902833528974,
      "arm2Length":488.6867367168975,
      "mainSegment":{
        "node_type":"AngledPropArm",
        "armLength":162.39471568196052,
        "motor":{
          "motorType":"t_motor_AT4120KV500"
        },
        "prop":{
          "propType":"apc_propellers_16x4E"
        }
      }
    },
    "middleSegment":{
      "node_type":"PropArm",
      "armLength":54.58931164692565,
      "motor":{
        "motorType":"t_motor_MN5208KV340"
      },
      "prop":{
        "propType":"apc_propellers_15_5x12W"
      },
      "flange":{
        "offset":-13.501675697437662,
        "angle":270.0
      }
    },
    "rearSegment":{
      "node_type":"PropArm",
      "armLength":225.84389114150423,
      "motor":{
        "motorType":"t_motor_MN5212KV340"
      },
      "prop":{
        "propType":"apc_propellers_14x7"
      },
      "flange":{
        "offset":-7.062998606352679,
        "angle":0.0
      }
    }
  },
  "fuselageWithComponents":{
    "node_type":"SingleBatteryFuselageWithComponents",
    "battery":{
      "batteryType":"TurnigyGraphene4000mAh3S75C"
    },
    "fuselage":{
      "length":145.0,
      "vertDiameter":76.5,
      "horzDiameter":327.9,
      "floorHeight":12.75,
      "batteryX":0.0,
      "batteryY":6.0,
      "rpmX":0.0,
      "rpmY":-99.3,
      "autoPilotX":0.0,
      "autoPilotY":43.0,
      "currentX":0.0,
      "currentY":-79.15,
      "voltageX":0.0,
      "voltageY":96.8,
      "gpsX":0.0,
      "gpsY":-39.0,
      "varioX":0.0,
      "varioY":75.15
    }
  }
}