{
  "generator_version":"UAV2_gen12",
  "name":"design_37016_d3634497603245c1a38205bc1e0dcfd5_dw_dl",
  "hub":{
    "node_type":"ConnectedHub6_2_2_2",
    "frontSegment":{
      "node_type":"AngledPropArm",
      "armLength":444.1468662318991,
      "motor":{
        "motorType":"t_motor_MN4010KV475"
      },
      "prop":{
        "propType":"apc_propellers_18x5_5MR"
      }
    },
    "middleSegment":{
      "node_type":"SidewaysBendSegment",
      "angle":-90.0,
      "armLength":232.77497214358178,
      "mainSegment":{
        "node_type":"PropArm",
        "armLength":259.49385729951,
        "motor":{
          "motorType":"t_motor_MN5208KV340"
        },
        "prop":{
          "propType":"apc_propellers_15x8"
        },
        "flange":{
          "offset":-38.55558173383062,
          "angle":90.0
        }
      }
    },
    "rearSegment":{
      "node_type":"AngledPropArm",
      "armLength":288.4253790709911,
      "motor":{
        "motorType":"t_motor_MN5212KV420"
      },
      "prop":{
        "propType":"apc_propellers_16x4W"
      }
    }
  },
  "fuselageWithComponents":{
    "node_type":"DualBatteryFuselageWithComponents",
    "battery":{
      "batteryType":"TurnigyGraphene1200mAh6S75C"
    },
    "fuselage":{
      "length":151.0,
      "vertDiameter":52.5,
      "horzDiameter":353.4,
      "floorHeight":8.75,
      "battery1X":-37.75,
      "battery1Y":6.0,
      "battery2X":38.75,
      "battery2Y":6.0,
      "rpmX":0.0,
      "rpmY":-107.8,
      "autoPilotX":0.0,
      "autoPilotY":51.5,
      "currentX":0.0,
      "currentY":-87.65,
      "voltageX":0.0,
      "voltageY":105.3,
      "gpsX":0.0,
      "gpsY":-47.5,
      "varioX":0.0,
      "varioY":83.65
    }
  }
}