{
  "generator_version":"UAV2_gen12",
  "name":"design_2623_ca45f301cabb4b60b157b831827163df_s",
  "hub":{
    "node_type":"ConnectedHub3_2_1",
    "angle":180.0,
    "centerSegment":{
      "node_type":"PropArm",
      "armLength":335.56296259211956,
      "motor":{
        "motorType":"t_motor_AT4130KV450"
      },
      "prop":{
        "propType":"apc_propellers_15x6"
      },
      "flange":{
        "offset":12.040066647889361,
        "angle":0.0
      }
    },
    "mainSegment":{
      "node_type":"PropArm",
      "armLength":317.8602130881021,
      "motor":{
        "motorType":"t_motor_MN4010KV475"
      },
      "prop":{
        "propType":"apc_propellers_17x7E"
      },
      "flange":{
        "offset":17.915041768816792,
        "angle":270.0
      }
    }
  },
  "fuselageWithComponents":{
    "node_type":"SingleBatteryFuselageWithComponents",
    "battery":{
      "batteryType":"TurnigyGraphene1000mAh6S75C"
    },
    "fuselage":{
      "length":84.0,
      "vertDiameter":52.5,
      "horzDiameter":350.4,
      "floorHeight":8.75,
      "batteryX":-4.5,
      "batteryY":6.0,
      "rpmX":-4.5,
      "rpmY":-106.8,
      "autoPilotX":-4.5,
      "autoPilotY":50.5,
      "currentX":-4.5,
      "currentY":-86.65,
      "voltageX":-4.5,
      "voltageY":104.3,
      "gpsX":-4.5,
      "gpsY":-46.5,
      "varioX":-4.5,
      "varioY":82.65
    }
  }
}